{
 "actions": [],
 "allow_rename": 1,
 "creation": "2024-09-04 16:45:20.585510",
 "doctype": "DocType",
 "editable_grid": 1,
 "engine": "InnoDB",
 "field_order": [
  "stiching_attribute_value",
  "set_item_attribute_value",
  "quantity",
  "category",
  "is_default"
 ],
 "fields": [
  {
   "fieldname": "quantity",
   "fieldtype": "Int",
   "in_list_view": 1,
   "label": "Quantity",
   "non_negative": 1
  },
  {
   "fieldname": "set_item_attribute_value",
   "fieldtype": "Link",
   "in_list_view": 1,
   "label": "Set Item Attribute Value",
   "options": "Item Attribute Value"
  },
  {
   "fieldname": "stiching_attribute_value",
   "fieldtype": "Link",
   "in_list_view": 1,
   "label": "Stiching Attribute Value",
   "options": "Item Attribute Value"
  },
  {
   "default": "0",
   "fieldname": "is_default",
   "fieldtype": "Check",
   "in_list_view": 1,
   "label": "Is Default"
  },
  {
   "fieldname": "category",
   "fieldtype": "Select",
   "in_list_view": 1,
   "label": "Category",
   "options": "\nBody\nCut & Sew\nMain Panel\nPlacket\nShorts\nRib",
   "reqd": 1
  }
 ],
 "grid_page_length": 50,
 "index_web_pages_for_search": 1,
 "istable": 1,
 "links": [],
 "modified": "2025-08-26 12:19:07.243429",
 "modified_by": "Administrator",
 "module": "Essdee Production",
 "name": "Stiching Item Detail",
 "owner": "Administrator",
 "permissions": [],
 "row_format": "Dynamic",
 "sort_field": "modified",
 "sort_order": "DESC",
 "states": []
}