{
 "absolute_value": 0,
 "align_labels_right": 0,
 "creation": "2024-10-24 16:52:20.946388",
 "css": "td,th{\n    width:50px;\n}\ntable{\n    width:700px;\n}\n.headings {\n    text-align: center;\n    border: 1px solid black; \n    font-weight: bold;\n    font-size:12px;\n    width:100px;\n}\n.headings-low {\n    text-align: center;\n    border: 1px solid black; \n    font-weight: bold;\n    font-size:12px;\n    width:100px;\n    \n}\n.datas-no{\n    text-align: center;\n    border: 1px solid black; \n    font-size:12px;\n    width:100px;\n}\n.datas {\n    text-align: center;\n    border: 1px solid black; \n    font-size:12px;\n    width:100px;\n}\n.print-format th{\n    color:black;\n    font-weight:600;\n}\n.datas-low {\n    text-align: center;\n    border: 1px solid black; \n    font-size:12px;\n    width:100px;\n}\n\n.print-format td, .print-format th {\n  padding: 6px !important;\n}\n\n.print-format td, .print-format th {\n  vertical-align: middle !important;\n}\n\n",
 "custom_format": 0,
 "default_print_language": "en",
 "disabled": 0,
 "doc_type": "Cutting LaySheet",
 "docstatus": 0,
 "doctype": "Print Format",
 "font_size": 14,
 "format_data": "[{\"fieldname\": \"print_heading_template\", \"fieldtype\": \"Custom HTML\", \"options\": \"<div class=\\\"print-heading\\\">\\t</div>\"}, {\"fieldtype\": \"Section Break\", \"label\": \"\"}, {\"fieldtype\": \"Column Break\"}, {\"fieldname\": \"_custom_html\", \"print_hide\": 0, \"label\": \"Custom HTML\", \"fieldtype\": \"HTML\", \"options\": \"<div>\\n    {% set width = doc.width_allowance + doc.width %}\\n    {% set length = doc.length_allowance + doc.length %}\\n    {% set size_length = { \\\"sizes\\\":0 }%}\\n    {% set date = get_created_date(doc.creation)%}\\n    {% set pcs_weight = doc.piece_weight | round(3)%}\\n    <table style=\\\"width:100%\\\">\\n        <tr>\\n            <td class=\\\"headings\\\" colspan=\\\"12\\\">Essdee Knitting Mills Private Limited</td>\\n        </tr>\\n        <tr>\\n            <td class=\\\"headings\\\" colspan=\\\"12\\\">\\n                <div style=\\\"display:flex; width:100%;\\\">    \\n                    <div style=\\\"width:62%;text-align:right;\\\">Cutting Department LaySheet</div>\\n                    <div style=\\\"width:38%;text-align:right;margin-right:5px;\\\">ID: {{doc.name}}</div>\\n                </div>\\n            </td>\\n        </tr>\\n        <tr>\\n            <td class=\\\"headings\\\" colspan=\\\"12\\\" style=\\\"width:100%;\\\">\\n                <div style=\\\"display:flex; width:100%;\\\">    \\n                    <div style=\\\"width:50%;text-align:left;margin-left:5px;\\\">Cutting Plan: ({{doc.cutting_plan}})</div>\\n                    <div style=\\\"width:50%;text-align:right;margin-right:5px;\\\">Marker: ({{doc.marker_name}})</div>\\n                </div>\\n            </td>\\n        </tr>\\n        <tr>\\n            <td class=\\\"headings\\\" colspan=\\\"1\\\">DATE</td>\\n            <td class=\\\"datas\\\"colspan=\\\"1\\\">{{date}}</td>\\n            <td class=\\\"headings\\\" colspan=\\\"2\\\">LOT NO</td>\\n            <td class=\\\"datas\\\" colspan=\\\"1\\\">{{doc.lot}}</td>\\n            <td class=\\\"headings\\\" colspan=\\\"2\\\">LAY NO</td>\\n            <td class=\\\"datas\\\" colspan=\\\"1\\\">{{doc.lay_no}}</td>\\n            <td class=\\\"headings\\\" colspan=\\\"2\\\">REQ LENGTH | WIDTH </td>\\n            <td class=\\\"datas\\\" colspan=\\\"2\\\">{{length}} | {{width}}</td>\\n        </tr>\\n        <tr>\\n            <td class=\\\"headings\\\" colspan=\\\"1\\\" rowspan=\\\"3\\\">STYLE</td>\\n            <td class=\\\"datas\\\" colspan=\\\"3\\\" rowspan=\\\"3\\\">{{doc.item}}</td>\\n            <td class=\\\"headings\\\" colspan=\\\"1\\\" rowspan=\\\"3\\\">FABRIC</td>\\n            <td class=\\\"datas\\\" colspan=\\\"3\\\" rowspan=\\\"3\\\"></td>\\n            <td class=\\\"headings\\\" colspan=\\\"2\\\" style=\\\"font-size:10px;\\\"rowspan=\\\"1\\\">ACT LENGTH</td>\\n            <td class=\\\"datas\\\" colspan=\\\"2\\\" rowspan=\\\"1\\\"></td>\\n        </tr>\\n        <tr>\\n            <td class=\\\"headings\\\" colspan=\\\"2\\\" style=\\\"font-size:10px;\\\" rowspan=\\\"1\\\">ACT WIDTH</td>\\n            <td class=\\\"datas\\\" colspan=\\\"2\\\" rowspan=\\\"1\\\"></td>\\n        </tr>\\n        <tr>\\n            <td class=\\\"headings\\\" colspan=\\\"2\\\" style=\\\"font-size:10px;\\\" rowspan=\\\"1\\\">SPREADER</td>\\n            <td class=\\\"datas\\\" colspan=\\\"2\\\" rowspan=\\\"1\\\">{{ doc.cutting_spreader }}</td>\\n        </tr>    \\n        <tr>\\n            <td class=\\\"headings-low\\\" colspan=\\\"2\\\">TOTAL BIT</td>\\n            <td class=\\\"datas\\\" colspan=\\\"1\\\"></td>\\n            <td class=\\\"headings-low\\\" colspan=\\\"2\\\">START TIME</td>\\n            <td class=\\\"datas\\\" colspan=\\\"3\\\"></td>\\n            <td class=\\\"headings-low\\\" colspan=\\\"2\\\">END TIME</td>\\n            <td class=\\\"datas\\\" colspan=\\\"2\\\"></td>\\n        </tr>\\n        {% if doc.selected_type == \\\"Machine\\\" %}\\n            <tr>\\n                {% set sizes = namespace(attrs=[]) %}\\n                <td class=\\\"headings-low\\\" colspan=\\\"1\\\">SIZES</td>\\n                {% for item in doc.cutting_marker_ratios %}\\n                    {% if item.size not in sizes.attrs %}\\n                        <td class=\\\"datas-no\\\" colspan=\\\"1\\\">{{ item.size }}</td>\\n                        {% set l = size_length[\\\"sizes\\\"] + 1 %}    \\n                        {% if size_length.update({\\\"sizes\\\": l}) %}{% endif %}\\n                        {% set sizes.attrs = sizes.attrs + [item.size] %}\\n                    {% endif %}    \\n                {% endfor %}\\n                {% if size_length.sizes < 10 %}\\n                    {% set loop_range = 10 - size_length.sizes %}\\n                    {% for i in range(0,loop_range)%}\\n                        <td class=\\\"datas-no\\\" colspan=\\\"1\\\"></td>\\n                    {% endfor %}\\n                {% endif %}\\n                <td class=\\\"datas-no\\\" colspan=\\\"1\\\">TOTAL</td>\\n            </tr>\\n            <tr>\\n                {% set sizes = namespace(attrs=[]) %}\\n                <td class=\\\"headings-low\\\" colspan=\\\"1\\\">RATIO</td>\\n                {% for item in doc.cutting_marker_ratios%}\\n                    {% if item.size not in sizes.attrs %}\\n                        <td class=\\\"datas-no\\\" colspan=\\\"1\\\">{{ item.ratio }}</td>\\n                        {% set sizes.attrs = sizes.attrs + [item.size] %}\\n                    {% endif %}\\n                {% endfor %}\\n                {% if size_length.sizes < 10 %}\\n                    {% set loop_range = 10 - size_length.sizes %}\\n                    {% for i in range(0,loop_range)%}\\n                        <td class=\\\"datas-no\\\" colspan=\\\"1\\\"></td>\\n                    {% endfor %}\\n                {% endif %}\\n                <td class=\\\"datas-no\\\" colspan=\\\"1\\\"></td>\\n            </tr>\\n        {% else %}\\n            <tr>\\n                <td class=\\\"headings-low\\\" colspan=\\\"1\\\">ORD QTY</td>\\n                {% for i in range(0, 10)%}\\n                    <td class=\\\"datas-no\\\" colspan=\\\"1\\\"></td>\\n                {% endfor %}\\n                <td class=\\\"datas-no\\\" colspan=\\\"1\\\"></td>\\n            </tr>\\n            <tr>\\n                <td class=\\\"headings-low\\\" colspan=\\\"1\\\">CUT QTY</td>\\n                {% for i in range(0,10)%}\\n                    <td class=\\\"datas-no\\\" colspan=\\\"1\\\"></td>\\n                {% endfor %}\\n                <td class=\\\"datas-no\\\" colspan=\\\"1\\\"></td>\\n            </tr>\\n            <tr>\\n                <td class=\\\"headings-low\\\" colspan=\\\"1\\\">BALANCE</td>\\n                {% for i in range(0,10)%}\\n                    <td class=\\\"datas-no\\\" colspan=\\\"1\\\"></td>\\n                {% endfor %}\\n                <td class=\\\"datas-no\\\" colspan=\\\"1\\\"></td>\\n            </tr>\\n        {% endif %}    \\n        \\n    </table>\\n    <table style=\\\"width: 100%; border-collapse: collapse; text-align: center;\\\">\\n        <thead>\\n            <tr style=\\\"width:100%;\\\">\\n                <th class=\\\"headings-low\\\" style=\\\"width: 13%;\\\">COLOR</th>\\n                <th class=\\\"headings-low\\\" style=\\\"width: 7%;\\\">SHADE</th>\\n                <th class=\\\"headings-low\\\" style=\\\"width: 10%;\\\">ROLLS/ ROLL NO</th>\\n                <th class=\\\"headings-low\\\" style=\\\"width: 15%;\\\">WEIGHT</th>\\n                <th class=\\\"headings-low\\\" style=\\\"width:5%;\\\">BITS</th>\\n                <th class=\\\"headings-low\\\" style=\\\"width: 10%;\\\">END_BIT</th>\\n                <th class=\\\"headings-low\\\" style=\\\"width: 10%;\\\">BALANCE</th>\\n                <th class=\\\"headings-low\\\" style=\\\"width: 10%;\\\">ACCESSORY <span style=\\\"font-size: 8px;\\\">(Folding/Piping)</span></th>\\n                <th class=\\\"headings-low\\\" style=\\\"width: 20%;\\\">REMARKS</th>\\n            </tr>\\n        </thead>\\n        <tbody>\\n            {% for item in doc.cutting_laysheet_details %}\\n            <tr>\\n                <td class=\\\"datas-low\\\" >{{ item.colour }}</td>\\n                <td class=\\\"datas-low\\\" >{{ item.shade }}</td>\\n                <td class=\\\"datas-low\\\" >{{ item.no_of_rolls }}</td>\\n                <td class=\\\"datas-low\\\" >{{ item.weight }}</td>\\n                <td class=\\\"datas-low\\\" >{{ item.no_of_bits }}</td>\\n                <td class=\\\"datas-low\\\" >{{ item.end_bit_weight }}</td>\\n                <td class=\\\"datas-low\\\" >{{ item.balance_weight}}</td>\\n                <td class=\\\"datas-low\\\" >{{ item.accessory_weight }}</td>\\n                <td class=\\\"datas-low\\\">{{ item.comments }}</td>\\n            </tr>\\n            {% endfor %}\\n            {% if doc.cutting_laysheet_details|length == 0 %}\\n            {% for i in range(0, 15) %}\\n            <tr>\\n                <td class=\\\"datas-low\\\" style=\\\"height:30px;\\\"></td>\\n                <td class=\\\"datas-low\\\"  style=\\\"height:30px;\\\"></td>\\n                <td class=\\\"datas-low\\\"  style=\\\"height:30px;\\\"></td>\\n                <td class=\\\"datas-low\\\"  style=\\\"height:30px;\\\"></td>\\n                <td class=\\\"datas-low\\\"  style=\\\"height:30px;\\\"></td>\\n                <td class=\\\"datas-low\\\"  style=\\\"height:30px;\\\"></td>\\n                <td class=\\\"datas-low\\\"  style=\\\"height:30px;\\\"></td>\\n                <td class=\\\"datas-low\\\"  style=\\\"height:30px;\\\"></td>\\n                <td class=\\\"datas-low\\\"  style=\\\"height:30px;\\\"></td>\\n            </tr>\\n            {% endfor %}\\n            {% endif %}\\n            <tr>\\n                <td class=\\\"headings-low\\\" colspan=\\\"1\\\">Total</td>\\n                <td class=\\\"headings-low\\\" colspan=\\\"1\\\"></td>\\n                {% if doc.no_of_rolls > 0 %}\\n                    <td class=\\\"headings-low\\\">{{doc.no_of_rolls}}</td>\\n                {% else %}\\n                    <td class=\\\"headings-low\\\"></td>\\n                {% endif %}\\n                {% if doc.weight > 0%}\\n                    <td class=\\\"headings-low\\\">{{doc.weight}}</td>\\n                {% else %}\\n                    <td class=\\\"headings-low\\\"></td>\\n                {% endif %}\\n                {% if doc.no_of_bits > 0 %}\\n                    <td class=\\\"headings-low\\\">{{doc.no_of_bits}}</td>\\n                {% else %}\\n                    <td class=\\\"headings-low\\\"></td>\\n                {% endif %}\\n                {% if doc.end_bit_weight > 0%}\\n                    <td class=\\\"headings-low\\\">{{doc.end_bit_weight}}</td>\\n                {% else %}\\n                    <td class=\\\"headings-low\\\"></td>\\n                {% endif %}\\n                {% set balance_weight = (doc.weight - doc.total_used_weight) | round(3) %}\\n                {% if balance_weight %}\\n                    <td class=\\\"headings-low\\\">{{ balance_weight }}</td>\\n                {% else %}\\n                    <td class=\\\"headings-low\\\"></td>\\n                {% endif %}\\n                {% if doc.accessory_weight > 0%}\\n                    <td class=\\\"headings-low\\\">{{doc.accessory_weight}}</td>\\n                {% else %}\\n                    <td class=\\\"headings-low\\\"></td>\\n                {% endif %}\\n                <td class=\\\"headings-low\\\" colspan=\\\"2\\\"></td>\\n            </tr>\\n            <tr>\\n                <td class=\\\"headings\\\" colspan=\\\"2\\\">Total Used Weight</td>\\n                {% if doc.total_used_weight > 0 %}\\n                    <td class=\\\"datas\\\">{{doc.total_used_weight}}</td>\\n                {% else %}\\n                    <td class=\\\"datas\\\"></td>\\n                {% endif %}\\n                <td class=\\\"headings\\\" colspan=\\\"2\\\">Required Pcs Weight</td>\\n                {% if doc.required_pcs_weight > 0 %}\\n                    <td class=\\\"datas\\\">{{ doc.required_pcs_weight }}</td>\\n                {% else %}\\n                    <td class=\\\"datas\\\"></td>\\n                {% endif %}\\n                <td class=\\\"headings\\\" colspan=\\\"2\\\">ACT Pcs Weight</td>\\n                {% if pcs_weight > 0 %}\\n                    <td class=\\\"datas\\\">{{ pcs_weight }}</td>\\n                {% else %}\\n                    <td class=\\\"datas\\\"></td>\\n                {% endif %}    \\n            </tr>\\n            <tr>\\n                <td class=\\\"headings\\\" style=\\\"height:70px\\\" colspan=\\\"2\\\"></td>\\n                <td class=\\\"headings\\\" style=\\\"height:70px\\\" colspan=\\\"2\\\"></td>\\n                <td class=\\\"headings\\\" style=\\\"height:70px\\\" colspan=\\\"2\\\"></td>\\n                <td class=\\\"headings\\\" style=\\\"height:70px\\\" colspan=\\\"3\\\"></td>\\n            </tr>\\n            <tr>\\n                <td class=\\\"headings\\\" colspan=\\\"2\\\">CUT BY</td>\\n                <td class=\\\"headings\\\" colspan=\\\"2\\\">SPREAD BY</td>\\n                <td class=\\\"headings\\\" colspan=\\\"2\\\">CHECKED BY</td>\\n                <td class=\\\"headings\\\" colspan=\\\"3\\\">APPROVED BY</td>\\n            </tr>\\n        </tbody>    \\n    </table>\\n\\n</div>\"}]",
 "idx": 0,
 "line_breaks": 0,
 "margin_bottom": 15.0,
 "margin_left": 15.0,
 "margin_right": 15.0,
 "margin_top": 15.0,
 "modified": "2025-08-12 11:25:06.004605",
 "modified_by": "Administrator",
 "module": "Production Api",
 "name": "Cutting LaySheet",
 "owner": "Administrator",
 "page_number": "Hide",
 "pdf_generator": "wkhtmltopdf",
 "print_format_builder": 0,
 "print_format_builder_beta": 0,
 "print_format_type": "Jinja",
 "raw_printing": 0,
 "show_section_headings": 0,
 "standard": "Yes"
}