{
 "actions": [],
 "creation": "2021-08-27 20:19:55.643855",
 "doctype": "DocType",
 "editable_grid": 1,
 "engine": "InnoDB",
 "field_order": [
  "lot",
  "qty"
 ],
 "fields": [
  {
   "fieldname": "lot",
   "fieldtype": "Link",
   "in_list_view": 1,
   "label": "Lot",
   "options": "Lot",
   "reqd": 1
  },
  {
   "fieldname": "qty",
   "fieldtype": "Float",
   "in_list_view": 1,
   "label": "Qty",
   "reqd": 1
  }
 ],
 "index_web_pages_for_search": 1,
 "istable": 1,
 "links": [],
 "modified": "2021-08-27 20:20:24.429115",
 "modified_by": "Administrator",
 "module": "Production Api",
 "name": "Purchase Order Item Lot Mapping Value",
 "owner": "Administrator",
 "permissions": [],
 "sort_field": "modified",
 "sort_order": "DESC",
 "track_changes": 1
}